log_analyzer/__init__.py
log_analyzer/__main__.py
log_analyzer/calculator.py
log_analyzer/clock.py
log_analyzer/config.py
log_analyzer/default_config.py
log_analyzer/process.py
log_analyzer/streamer.py
log_analyzer/patterns/__init__.py
log_analyzer/patterns/access_log_w3.py
log_analyzer/patterns/alert_default.py
log_analyzer/patterns/base.py
log_analyzer/persistence/__init__.py
log_analyzer/persistence/base.py
log_analyzer/persistence/memory.py
log_analyzer/processes/__init__.py
log_analyzer/processes/alert_manager.py
log_analyzer/processes/consumer.py
log_analyzer/processes/parser.py
tests/__init__.py
tests/conftest.py
log_analyzer-0.0.2.dist-info/METADATA
log_analyzer-0.0.2.dist-info/WHEEL
log_analyzer-0.0.2.dist-info/entry_points.txt
log_analyzer-0.0.2.dist-info/top_level.txt
log_analyzer-0.0.2.dist-info/RECORD
