Metadata-Version: 2.1
Name: log-analyzer
Version: 0.0.2
Summary: Log analyzer 
Home-page: https://github.com/yurilaaziz/log-analyzer
Author: Amine Ben Asker
Author-email: ben.asker.amine@gmail.com
License: GPLv3+
Download-URL: https://github.com/yurilaaziz/log_anaylzer/releases/tag/0.1
Keywords: Log Analyzer,W3 log,Log Parser
Platform: UNKNOWN
Classifier: Development Status :: 3 - Alpha
Classifier: Intended Audience :: Developers
Classifier: Topic :: Software Development :: Build Tools
Classifier: License :: OSI Approved :: MIT License
Classifier: Programming Language :: Python :: 3
Classifier: Programming Language :: Python :: 3.5
Classifier: Programming Language :: Python :: 3.6
Classifier: Programming Language :: Python :: 3.7
Requires-Dist: blessings (==1.7)
Requires-Dist: config42 (==0.3.1)
Requires-Dist: prettytable (==0.7.2)
Requires-Dist: pyyaml (==5.1)
